check_tls_certs.py
check_tls_certs-0.12.0.dist-info/METADATA
check_tls_certs-0.12.0.dist-info/RECORD
check_tls_certs-0.12.0.dist-info/WHEEL
check_tls_certs-0.12.0.dist-info/entry_points.txt
check_tls_certs-0.12.0.dist-info/top_level.txt
