Metadata-Version: 2.1
Name: check-tls-certs
Version: 0.12.0
Summary: Check TLS certificates of domains for expiration dates and more.
Home-page: https://github.com/fschulze/check-tls-certs
Author: UNKNOWN
Author-email: UNKNOWN
License: UNKNOWN
Platform: UNKNOWN
Classifier: Development Status :: 5 - Production/Stable
Classifier: Intended Audience :: System Administrators
Classifier: License :: OSI Approved :: MIT License
Classifier: Programming Language :: Python
Classifier: Programming Language :: Python :: 3.6
Classifier: Programming Language :: Python :: 3.7
Classifier: Programming Language :: Python :: 3.8
Requires-Dist: click
Requires-Dist: pyOpenSSL
